MANIFEST.in
README.md
setup.py
grunt/__init__.py
grunt/parse.py
grunt/render.py
grunt/template.html
grunt.egg-info/PKG-INFO
grunt.egg-info/SOURCES.txt
grunt.egg-info/dependency_links.txt
grunt.egg-info/entry_points.txt
grunt.egg-info/top_level.txt