Metadata-Version: 1.0
Name: grunt
Version: 0.1.1
Summary: Render a single-file HTML5 slideshow from a file of slide definitions
Home-page: UNKNOWN
Author: Ozan Onay
Author-email: ozan.onay@gmail.com
License: Apache
Platform: UNKNOWN
Classifier: Development Status :: 4 - Beta
Classifier: License :: OSI Approved :: Apache Software License
Classifier: Natural Language :: English
Classifier: Operating System :: OS Independent
Classifier: Programming Language :: Python
Classifier: Programming Language :: Python :: 2.5
Classifier: Programming Language :: Python :: 2.6
Classifier: Topic :: Documentation
